sick_json.py
sick_json-0.0.4.dist-info/METADATA
sick_json-0.0.4.dist-info/WHEEL
sick_json-0.0.4.dist-info/licenses/LICENSE
sick_json-0.0.4.dist-info/RECORD
