Metadata-Version: 2.1
Name: sick-json
Version: 0.0.4
Summary: A simple tool to parse the non-normal JSON that LLM responds to.
Author-email: Kim Minjong <make.dirty.code@gmail.com>
License-File: LICENSE
Classifier: License :: OSI Approved :: MIT License
Classifier: Operating System :: OS Independent
Classifier: Programming Language :: Python :: 3
Requires-Python: >=3.5
Requires-Dist: pyjson5
